fundrives/__init__.py
fundrives/baidu/__init__.py
fundrives/baidu/api.py
fundrives/baidu/errors.py
fundrives/baidu/inner.py
fundrives/baidu/pcs.py
fundrives/baidu/phone.py
fundrives/baidu/utils.py
fundrives/baidu/common/cache.py
fundrives/baidu/common/concurrent.py
fundrives/baidu/common/constant.py
fundrives/baidu/common/crypto.py
fundrives/baidu/common/date.py
fundrives/baidu/common/downloader.py
fundrives/baidu/common/event.py
fundrives/baidu/common/file_type.py
fundrives/baidu/common/io.py
fundrives/baidu/common/keyboard.py
fundrives/baidu/common/localstorage.py
fundrives/baidu/common/log.py
fundrives/baidu/common/net.py
fundrives/baidu/common/number.py
fundrives/baidu/common/path.py
fundrives/baidu/common/platform.py
fundrives/baidu/common/progress_bar.py
fundrives/baidu/common/random.py
fundrives/baidu/common/simple_cipher.py
fundrives/baidu/common/url.py
fundrive_baidu-1.0.10.dist-info/METADATA
fundrive_baidu-1.0.10.dist-info/WHEEL
fundrive_baidu-1.0.10.dist-info/top_level.txt
fundrive_baidu-1.0.10.dist-info/RECORD
